ChangeLog
LICENSE
MANIFEST.in
README.rst
setup.py
jsonmerge/__init__.py
jsonmerge/descenders.py
jsonmerge/exceptions.py
jsonmerge/jsonvalue.py
jsonmerge/resolver.py
jsonmerge/strategies.py
jsonmerge.egg-info/PKG-INFO
jsonmerge.egg-info/SOURCES.txt
jsonmerge.egg-info/dependency_links.txt
jsonmerge.egg-info/requires.txt
jsonmerge.egg-info/top_level.txt
tests/__init__.py
tests/test_jsonmerge.py
tests/test_jsonvalue.py
tests/test_readme.py