Metadata-Version: 1.1
Name: jsonmerge
Version: 1.5.0
Summary: Merge a series of JSON documents.
Home-page: UNKNOWN
Author: Tomaz Solc
Author-email: tomaz.solc@tablix.org
License: MIT
Platform: UNKNOWN
Classifier: License :: OSI Approved :: MIT License
Classifier: Programming Language :: Python
Classifier: Programming Language :: Python :: 2
Classifier: Programming Language :: Python :: 3
Classifier: Intended Audience :: Developers
